jen/__init__.py
jen/assistant.py
jen/configure.py
jen/functions.py
jen/news.py
JenAssistant-1.0.0.dist-info/LICENSE.txt
JenAssistant-1.0.0.dist-info/METADATA
JenAssistant-1.0.0.dist-info/WHEEL
JenAssistant-1.0.0.dist-info/top_level.txt
JenAssistant-1.0.0.dist-info/RECORD
