Metadata-Version: 2.1
Name: JenAssistant
Version: 1.0.0
Summary: A package which can be used for virtual assistants
Home-page: https://github.com/VishalShenoy2002/JEN
Author: Vishal Balakrishna Shenoy
Author-email: vishal.bshenoy@gmail.com
License: UNKNOWN
Project-URL: Bug Tracker, https://github.com/VishalShenoy2002/JEN/issues
Keywords: python,virtual assistant,assistant,Jen,Jen Assistant,JEN
Platform: UNKNOWN
Classifier: Programming Language :: Python :: 3
Classifier: License :: OSI Approved :: MIT License
Classifier: Operating System :: OS Independent
Requires-Python: >=3.6
License-File: LICENSE.txt
Requires-Dist: pyttsx3
Requires-Dist: SpeechRecognition
Requires-Dist: pyautogui
Requires-Dist: werkzeug
Requires-Dist: pipwin
Requires-Dist: requests
Requires-Dist: beautifulsoup4
